DateKeeper/__init__.py
DateKeeper/check.py
DateKeeper/edit.py
datekeeper-0.0.2.dist-info/METADATA
datekeeper-0.0.2.dist-info/WHEEL
datekeeper-0.0.2.dist-info/top_level.txt
datekeeper-0.0.2.dist-info/RECORD
