Metadata-Version: 2.1
Name: datekeeper
Version: 0.0.2
Summary: Simple daily event keeper.
Home-page: https://github.com/bogdanmishalo/DateKeeper
Author: bogdan_m
Author-email: bogdanmdosss@gmail.com
Project-URL: GitHub, https://github.com/bogdanmishalo/DateKeeper
Keywords: calendar keep date
Classifier: Programming Language :: Python :: 3.11
Classifier: License :: OSI Approved :: MIT License
Classifier: Operating System :: OS Independent
Requires-Python: >=3.6
